fprint.cpython-37m-x86_64-linux-gnu.so
fprint/fprint.c
fprint/fprint.pxd
fprint/fprint.pyx
fprintw-0.2.1.dist-info/LICENSE.txt
fprintw-0.2.1.dist-info/METADATA
fprintw-0.2.1.dist-info/RECORD
fprintw-0.2.1.dist-info/WHEEL
fprintw-0.2.1.dist-info/top_level.txt
