Metadata-Version: 2.1
Name: fprintw
Version: 0.2.1
Summary: Wrapper for libfprint v0.99
Home-page: https://github.com/gtors/fprint
Author: Andrey Torsunov
License: UNKNOWN
Project-URL: Source, https://github.com/gtors/fprint
Keywords: fingerprint,fprint
Platform: UNKNOWN
Classifier: Programming Language :: Python :: 3.7
